[{"id":"1117020001","district_id":"1117020","name":"RIME RAYA","postal_code":"24656"},{"id":"1117020002","district_id":"1117020","name":"SINGAH MULO","postal_code":"24655"},{"id":"1117020003","district_id":"1117020","name":"ALUR GADING","postal_code":"23773"},{"id":"1117020004","district_id":"1117020","name":"BLANG RAKAL","postal_code":"24553"},{"id":"1117020005","district_id":"1117020","name":"NEGERI ANTARA","postal_code":"24553"},{"id":"1117020006","district_id":"1117020","name":"BLANG ARA","postal_code":"24553"},{"id":"1117020007","district_id":"1117020","name":"GEMASIH","postal_code":"24553"},{"id":"1117020008","district_id":"1117020","name":"PULO INTAN","postal_code":"24553"},{"id":"1117020009","district_id":"1117020","name":"RATA ARA","postal_code":"24553"},{"id":"1117020010","district_id":"1117020","name":"MUSARA 58","postal_code":"99571"},{"id":"1117020011","district_id":"1117020","name":"MUSARA PAKAT","postal_code":"24553"},{"id":"1117020012","district_id":"1117020","name":"WEH PORAK","postal_code":"59172"},{"id":"1117020013","district_id":"1117020","name":"SIMPANG LANCANG","postal_code":"24553"},{"id":"1117020014","district_id":"1117020","name":"BENER MERIAH","postal_code":"24553"},{"id":"1117020015","district_id":"1117020","name":"PERDAMAIAN","postal_code":"37482"},{"id":"1117020016","district_id":"1117020","name":"ULU NARON","postal_code":"24553"},{"id":"1117020017","district_id":"1117020","name":"TAMAN FIRDAUS","postal_code":"24553"},{"id":"1117020018","district_id":"1117020","name":"BINTANG BERANGUN","postal_code":"24553"},{"id":"1117020019","district_id":"1117020","name":"UNING EMAS","postal_code":"24581"},{"id":"1117020020","district_id":"1117020","name":"PANCAR JELOBOK","postal_code":"24553"},{"id":"1117020021","district_id":"1117020","name":"ALUR CINCIN","postal_code":"20858"},{"id":"1117020022","district_id":"1117020","name":"PANTAN SINAKU","postal_code":"24553"},{"id":"1117020023","district_id":"1117020","name":"PANTAN LAH","postal_code":"24553"}]