[{"id":"1171011001","district_id":"1171011","name":"ULEE PATA","postal_code":"23235"},{"id":"1171011002","district_id":"1171011","name":"LAMJAMEE","postal_code":"23235"},{"id":"1171011003","district_id":"1171011","name":"LAMPOH DAYA","postal_code":"23235"},{"id":"1171011004","district_id":"1171011","name":"EMPEROM","postal_code":"23236"},{"id":"1171011005","district_id":"1171011","name":"GEUCEU MEUNARA","postal_code":"23241"},{"id":"1171011006","district_id":"1171011","name":"LAMTEMEN BARAT","postal_code":"23230"},{"id":"1171011007","district_id":"1171011","name":"BITAI","postal_code":"23235"},{"id":"1171011008","district_id":"1171011","name":"LAMTEMEN TIMUR","postal_code":"23230"},{"id":"1171011009","district_id":"1171011","name":"PUNGE BLANG CUT","postal_code":"23234"}]