[{"id":"1405025001","district_id":"1405025","name":"KUALA GASIB","postal_code":"28671"},{"id":"1405025002","district_id":"1405025","name":"TELUK RIMBA","postal_code":"28671"},{"id":"1405025003","district_id":"1405025","name":"PANGKALAN PISANG","postal_code":"28671"},{"id":"1405025004","district_id":"1405025","name":"KERANJI GUGUH","postal_code":"28671"},{"id":"1405025005","district_id":"1405025","name":"EMPANG PANDAN","postal_code":"28671"},{"id":"1405025006","district_id":"1405025","name":"SENGKEMANG","postal_code":"28671"},{"id":"1405025007","district_id":"1405025","name":"RANTAU PANJANG","postal_code":"24782"},{"id":"1405025008","district_id":"1405025","name":"BUATAN II","postal_code":"28671"},{"id":"1405025009","district_id":"1405025","name":"BUATAN I","postal_code":"28671"},{"id":"1405025010","district_id":"1405025","name":"SRI GEMILANG","postal_code":"28671"},{"id":"1405025011","district_id":"1405025","name":"TASIK SEMINAI","postal_code":"28671"}]