[{"id":"1502061009","district_id":"1502061","name":"MUARA JERNIH","postal_code":"37356"},{"id":"1502061010","district_id":"1502061","name":"PULAU ARO","postal_code":"37482"},{"id":"1502061011","district_id":"1502061","name":"KAPUK","postal_code":"30653"},{"id":"1502061012","district_id":"1502061","name":"RANTAU NGARAU","postal_code":"70675"},{"id":"1502061013","district_id":"1502061","name":"MUARO SEKETUK","postal_code":"26353"},{"id":"1502061014","district_id":"1502061","name":"MEDAN BARU","postal_code":"37356"}]