[{"id":"1571030001","district_id":"1571030","name":"KEBUN HANDIL","postal_code":"36137"},{"id":"1571030002","district_id":"1571030","name":"JELUTUNG","postal_code":"79453"},{"id":"1571030003","district_id":"1571030","name":"PAYO LEBAR","postal_code":"37482"},{"id":"1571030004","district_id":"1571030","name":"LEBAK BANDUNG","postal_code":"36135"},{"id":"1571030005","district_id":"1571030","name":"CEMPAKA PUTIH","postal_code":"15412"},{"id":"1571030006","district_id":"1571030","name":"TALANG JAUH","postal_code":"36133"},{"id":"1571030007","district_id":"1571030","name":"HANDIL JAYA","postal_code":"36137"}]