[{"id":"1602010001","district_id":"1602010","name":"CAHYA BUMI","postal_code":"30657"},{"id":"1602010002","district_id":"1602010","name":"BUMI ARJO","postal_code":"30657"},{"id":"1602010003","district_id":"1602010","name":"CAHYA TANI","postal_code":"30657"},{"id":"1602010004","district_id":"1602010","name":"DABUK REJO","postal_code":"30657"},{"id":"1602010005","district_id":"1602010","name":"SUKAMULYA","postal_code":"46151"},{"id":"1602010007","district_id":"1602010","name":"TEBING SULUH","postal_code":"30657"},{"id":"1602010008","district_id":"1602010","name":"CAHYA MAJU","postal_code":"30657"},{"id":"1602010009","district_id":"1602010","name":"TULUNG HARAPAN","postal_code":"32185"},{"id":"1602010010","district_id":"1602010","name":"BUMI AGUNG","postal_code":"34763"},{"id":"1602010011","district_id":"1602010","name":"SINDANG SARI","postal_code":"15560"},{"id":"1602010012","district_id":"1602010","name":"SUMBER AGUNG","postal_code":"34595"},{"id":"1602010014","district_id":"1602010","name":"KEPAHYANG","postal_code":"30657"},{"id":"1602010015","district_id":"1602010","name":"TUGUMULYO","postal_code":"30657"},{"id":"1602010016","district_id":"1602010","name":"TUGU AGUNG","postal_code":"30657"},{"id":"1602010017","district_id":"1602010","name":"TUGU JAYA","postal_code":"30657"},{"id":"1602010018","district_id":"1602010","name":"MEKAR JAYA","postal_code":"34683"},{"id":"1602010019","district_id":"1602010","name":"SUMBER MAKMUR","postal_code":"34682"},{"id":"1602010020","district_id":"1602010","name":"BUMI ARJO MAKMUR","postal_code":"30657"},{"id":"1602010021","district_id":"1602010","name":"CAHYA MAKMUR","postal_code":"30657"}]