[{"id":"1603010001","district_id":"1603010","name":"PENINDAIAN","postal_code":"31356"},{"id":"1603010002","district_id":"1603010","name":"BABATAN","postal_code":"60227"},{"id":"1603010003","district_id":"1603010","name":"MUARA DUA","postal_code":"35679"},{"id":"1603010004","district_id":"1603010","name":"PULAU PANGGUNG","postal_code":"35679"},{"id":"1603010005","district_id":"1603010","name":"MUARA DANAU","postal_code":"36554"},{"id":"1603010006","district_id":"1603010","name":"PENYANDINGAN","postal_code":"35379"},{"id":"1603010007","district_id":"1603010","name":"TANAH ABANG","postal_code":"38887"},{"id":"1603010008","district_id":"1603010","name":"KARYA NYATA","postal_code":"31356"},{"id":"1603010009","district_id":"1603010","name":"PAGAR AGUNG","postal_code":"38883"},{"id":"1603010010","district_id":"1603010","name":"PERAPAU","postal_code":"31356"}]