[{"id":"1701060013","district_id":"1701060","name":"PADANG LEBAR","postal_code":"38552"},{"id":"1701060014","district_id":"1701060","name":"ANGGUT","postal_code":"38571"},{"id":"1701060015","district_id":"1701060","name":"GEDUNG AGUNG","postal_code":"35679"},{"id":"1701060016","district_id":"1701060","name":"TANJUNG ERAN","postal_code":"31593"},{"id":"1701060017","district_id":"1701060","name":"TANJUNG AUR I","postal_code":"38571"},{"id":"1701060018","district_id":"1701060","name":"PUDING","postal_code":"36371"},{"id":"1701060019","district_id":"1701060","name":"AIR UMBAN","postal_code":"38571"},{"id":"1701060020","district_id":"1701060","name":"MASAT","postal_code":"38571"},{"id":"1701060024","district_id":"1701060","name":"ULAK LEBAR","postal_code":"32157"},{"id":"1701060025","district_id":"1701060","name":"SEBILO","postal_code":"38571"},{"id":"1701060026","district_id":"1701060","name":"GANJUH","postal_code":"38571"},{"id":"1701060027","district_id":"1701060","name":"KOTA BUMI","postal_code":"38571"},{"id":"1701060028","district_id":"1701060","name":"BATU BANDUNG","postal_code":"31661"},{"id":"1701060029","district_id":"1701060","name":"BERINGIN DATAR","postal_code":"38571"},{"id":"1701060030","district_id":"1701060","name":"PADANG MUMPO","postal_code":"38571"},{"id":"1701060031","district_id":"1701060","name":"PADANG TAMBAK","postal_code":"34884"}]