[{"id":"1709041001","district_id":"1709041","name":"LUBUK PUAR","postal_code":"38383"},{"id":"1709041002","district_id":"1709041","name":"PUNJUNG","postal_code":"63561"},{"id":"1709041003","district_id":"1709041","name":"BAJAK III","postal_code":"38383"},{"id":"1709041004","district_id":"1709041","name":"KOMERING","postal_code":"38383"},{"id":"1709041005","district_id":"1709041","name":"ARGA INDAH II","postal_code":"38383"},{"id":"1709041006","district_id":"1709041","name":"CURUP","postal_code":"31314"},{"id":"1709041007","district_id":"1709041","name":"KARANG PANGGUNG","postal_code":"31625"},{"id":"1709041008","district_id":"1709041","name":"LUBUK PENDAM","postal_code":"38374"},{"id":"1709041009","district_id":"1709041","name":"RAJAK BESI","postal_code":"87271"},{"id":"1709041010","district_id":"1709041","name":"SUSUP","postal_code":"38383"},{"id":"1709041011","district_id":"1709041","name":"PAGAR AGUNG","postal_code":"38883"},{"id":"1709041012","district_id":"1709041","name":"DURIAN LEBAR","postal_code":"38383"},{"id":"1709041013","district_id":"1709041","name":"TABA GEMANTUNG","postal_code":"38386"},{"id":"1709041014","district_id":"1709041","name":"PUNGGUK JAYA","postal_code":"38383"},{"id":"1709041015","district_id":"1709041","name":"PAGAR BESI","postal_code":"38383"}]