[{"id":"1805070001","district_id":"1805070","name":"REJO BASUKI","postal_code":"34155"},{"id":"1805070002","district_id":"1805070","name":"REJO ASRI","postal_code":"34155"},{"id":"1805070003","district_id":"1805070","name":"RUKTI ENDAH","postal_code":"34155"},{"id":"1805070004","district_id":"1805070","name":"RAMA GUNAWAN","postal_code":"34155"},{"id":"1805070005","district_id":"1805070","name":"RAMA DEWA","postal_code":"34155"},{"id":"1805070006","district_id":"1805070","name":"RATNA KHATON","postal_code":"34155"},{"id":"1805070007","district_id":"1805070","name":"RAMAYANA","postal_code":"34155"},{"id":"1805070008","district_id":"1805070","name":"RAMA INDERA","postal_code":"34155"},{"id":"1805070009","district_id":"1805070","name":"RUKTI HARJO","postal_code":"34155"},{"id":"1805070010","district_id":"1805070","name":"RAMA MURTI","postal_code":"34155"},{"id":"1805070011","district_id":"1805070","name":"RAMA UTAMA","postal_code":"34371"},{"id":"1805070012","district_id":"1805070","name":"RAMA NIRWANA","postal_code":"34155"},{"id":"1805070013","district_id":"1805070","name":"BUYUT BARU","postal_code":"34155"},{"id":"1805070014","district_id":"1805070","name":"RAMA KELANDUNGAN","postal_code":"34155"}]