[{"id":"1906020001","district_id":"1906020","name":"LILANGAN","postal_code":"33562"},{"id":"1906020002","district_id":"1906020","name":"JANGKAR ASAM","postal_code":"33562"},{"id":"1906020003","district_id":"1906020","name":"GANTUNG","postal_code":"33562"},{"id":"1906020004","district_id":"1906020","name":"SELINGSING","postal_code":"33562"},{"id":"1906020008","district_id":"1906020","name":"LIMBONGAN","postal_code":"33562"},{"id":"1906020009","district_id":"1906020","name":"BATU PENYU","postal_code":"33562"},{"id":"1906020010","district_id":"1906020","name":"LENGGANG","postal_code":"33562"}]