[{"id":"3210041002","district_id":"3210041","name":"HEGARMANAH","postal_code":"45363"},{"id":"3210041003","district_id":"3210041","name":"SINDANGPALA","postal_code":"45468"},{"id":"3210041004","district_id":"3210041","name":"DARMALARANG","postal_code":"45468"},{"id":"3210041005","district_id":"3210041","name":"SUNIABARU","postal_code":"45468"},{"id":"3210041006","district_id":"3210041","name":"SANGIANG","postal_code":"15520"},{"id":"3210041007","district_id":"3210041","name":"SUNIA","postal_code":"45468"},{"id":"3210041008","district_id":"3210041","name":"KAREO","postal_code":"42177"},{"id":"3210041009","district_id":"3210041","name":"BANJARAN","postal_code":"53362"},{"id":"3210041010","district_id":"3210041","name":"KAGOK","postal_code":"52411"},{"id":"3210041011","district_id":"3210041","name":"CIMEONG","postal_code":"45468"},{"id":"3210041012","district_id":"3210041","name":"PANYINDANGAN","postal_code":"45392"},{"id":"3210041013","district_id":"3210041","name":"GIRIMULYA","postal_code":"94972"}]