[{"id":"3308020001","district_id":"3308020","name":"GIRIPURNO","postal_code":"56255"},{"id":"3308020002","district_id":"3308020","name":"GIRITENGAH","postal_code":"56553"},{"id":"3308020003","district_id":"3308020","name":"TUKSONGO","postal_code":"56553"},{"id":"3308020004","district_id":"3308020","name":"MAJAKSINGI","postal_code":"56553"},{"id":"3308020005","district_id":"3308020","name":"KENALAN","postal_code":"56193"},{"id":"3308020006","district_id":"3308020","name":"BIGARAN","postal_code":"56553"},{"id":"3308020007","district_id":"3308020","name":"SAMBENG","postal_code":"54224"},{"id":"3308020008","district_id":"3308020","name":"CANDIREJO","postal_code":"56351"},{"id":"3308020009","district_id":"3308020","name":"NGARGOGONDO","postal_code":"56553"},{"id":"3308020010","district_id":"3308020","name":"WANUREJO","postal_code":"56553"},{"id":"3308020011","district_id":"3308020","name":"BOROBUDUR","postal_code":"56553"},{"id":"3308020012","district_id":"3308020","name":"TANJUNGSARI","postal_code":"57672"},{"id":"3308020013","district_id":"3308020","name":"KARANGANYAR","postal_code":"56362"},{"id":"3308020014","district_id":"3308020","name":"KARANGREJO","postal_code":"56361"},{"id":"3308020015","district_id":"3308020","name":"NGADIHARJO","postal_code":"56553"},{"id":"3308020016","district_id":"3308020","name":"KEBONSARI","postal_code":"62317"},{"id":"3308020017","district_id":"3308020","name":"TEGALARUM","postal_code":"59154"},{"id":"3308020018","district_id":"3308020","name":"KEMBANGLIMUS","postal_code":"56553"},{"id":"3308020019","district_id":"3308020","name":"WRINGINPUTIH","postal_code":"56553"},{"id":"3308020020","district_id":"3308020","name":"BUMIHARJO","postal_code":"57671"}]