[{"id":"3327040001","district_id":"3327040","name":"TUNDAGAN","postal_code":"52357"},{"id":"3327040002","district_id":"3327040","name":"TLAGASANA","postal_code":"52357"},{"id":"3327040003","district_id":"3327040","name":"BONGAS","postal_code":"41254"},{"id":"3327040004","district_id":"3327040","name":"CIKADU","postal_code":"46153"},{"id":"3327040005","district_id":"3327040","name":"CAWET","postal_code":"52357"},{"id":"3327040006","district_id":"3327040","name":"MEDAYU","postal_code":"50776"},{"id":"3327040007","district_id":"3327040","name":"PAGELARAN","postal_code":"43187"},{"id":"3327040008","district_id":"3327040","name":"BODAS","postal_code":"52357"},{"id":"3327040009","district_id":"3327040","name":"JOJOGAN","postal_code":"56354"},{"id":"3327040010","district_id":"3327040","name":"MAJALANGU","postal_code":"52357"},{"id":"3327040011","district_id":"3327040","name":"TAMBI","postal_code":"56354"},{"id":"3327040012","district_id":"3327040","name":"WATUKUMPUL","postal_code":"56254"},{"id":"3327040013","district_id":"3327040","name":"GAPURA","postal_code":"79462"},{"id":"3327040014","district_id":"3327040","name":"MAJAKERTA","postal_code":"52357"},{"id":"3327040015","district_id":"3327040","name":"WISNU","postal_code":"52357"}]