[{"id":"3506010002","district_id":"3506010","name":"NGADI","postal_code":"97611"},{"id":"3506010003","district_id":"3506010","name":"KRANDING","postal_code":"64162"},{"id":"3506010004","district_id":"3506010","name":"MAESAN","postal_code":"64162"},{"id":"3506010005","district_id":"3506010","name":"PONGGOK","postal_code":"63518"},{"id":"3506010006","district_id":"3506010","name":"PETUNGROTO","postal_code":"64162"},{"id":"3506010007","district_id":"3506010","name":"PAMONGAN","postal_code":"64162"},{"id":"3506010008","district_id":"3506010","name":"KEDAWUNG","postal_code":"56281"},{"id":"3506010009","district_id":"3506010","name":"PLOSO","postal_code":"57695"},{"id":"3506010010","district_id":"3506010","name":"TAMBIBENDO","postal_code":"64162"},{"id":"3506010011","district_id":"3506010","name":"KRATON","postal_code":"52112"},{"id":"3506010012","district_id":"3506010","name":"BLIMBING","postal_code":"66293"},{"id":"3506010013","district_id":"3506010","name":"JUGO","postal_code":"62261"},{"id":"3506010014","district_id":"3506010","name":"MOJO","postal_code":"60285"},{"id":"3506010015","district_id":"3506010","name":"MLATI","postal_code":"63581"},{"id":"3506010016","district_id":"3506010","name":"SURAT","postal_code":"64162"},{"id":"3506010017","district_id":"3506010","name":"SUKOANYAR","postal_code":"66273"},{"id":"3506010018","district_id":"3506010","name":"KENITEN","postal_code":"63412"},{"id":"3506010019","district_id":"3506010","name":"MONDO","postal_code":"64162"},{"id":"3506010020","district_id":"3506010","name":"PETOK","postal_code":"64162"}]