[{"id":"3507210001","district_id":"3507210","name":"SUMBERSUKO","postal_code":"65158"},{"id":"3507210002","district_id":"3507210","name":"MENDALANWANGI","postal_code":"65158"},{"id":"3507210003","district_id":"3507210","name":"SITIREJO","postal_code":"59174"},{"id":"3507210004","district_id":"3507210","name":"PARANGARGO","postal_code":"65158"},{"id":"3507210005","district_id":"3507210","name":"GONDOWANGI","postal_code":"65158"},{"id":"3507210006","district_id":"3507210","name":"PANDANREJO","postal_code":"54175"},{"id":"3507210008","district_id":"3507210","name":"SUKODADI","postal_code":"67291"},{"id":"3507210009","district_id":"3507210","name":"SIDORAHAYU","postal_code":"30758"},{"id":"3507210010","district_id":"3507210","name":"JEDONG","postal_code":"65158"},{"id":"3507210011","district_id":"3507210","name":"DALISODO","postal_code":"65158"},{"id":"3507210012","district_id":"3507210","name":"PANDANLANDUNG","postal_code":"65158"}]