[{"id":"3518140001","district_id":"3518140","name":"JATIREJO","postal_code":"57678"},{"id":"3518140002","district_id":"3518140","name":"PLOSO","postal_code":"57695"},{"id":"3518140003","district_id":"3518140","name":"KRAMAT","postal_code":"56271"},{"id":"3518140004","district_id":"3518140","name":"PAYAMAN","postal_code":"64418"},{"id":"3518140005","district_id":"3518140","name":"KARTOHARJO","postal_code":"63218"},{"id":"3518140006","district_id":"3518140","name":"CANGKRINGAN","postal_code":"64415"},{"id":"3518140007","district_id":"3518140","name":"BOGO","postal_code":"64415"},{"id":"3518140008","district_id":"3518140","name":"KAUMAN","postal_code":"56364"},{"id":"3518140009","district_id":"3518140","name":"GANUNG KIDUL","postal_code":"64419"},{"id":"3518140010","district_id":"3518140","name":"MANGUN DIKARAN","postal_code":"64419"},{"id":"3518140011","district_id":"3518140","name":"WERUNGOTOK","postal_code":"64419"},{"id":"3518140012","district_id":"3518140","name":"BEGADUNG","postal_code":"64413"},{"id":"3518140013","district_id":"3518140","name":"RINGIN ANOM","postal_code":"63284"},{"id":"3518140014","district_id":"3518140","name":"KEDUNG DOWO","postal_code":"68371"},{"id":"3518140015","district_id":"3518140","name":"BALONG PACUL","postal_code":"64419"}]