[{"id":"5105010001","district_id":"5105010","name":"SAKTI","postal_code":"91991"},{"id":"5105010002","district_id":"5105010","name":"BUNGA MEKAR","postal_code":"80771"},{"id":"5105010003","district_id":"5105010","name":"BATUMADEG","postal_code":"80771"},{"id":"5105010005","district_id":"5105010","name":"BATUKANDIK","postal_code":"80771"},{"id":"5105010006","district_id":"5105010","name":"SEKARTAJI","postal_code":"80771"},{"id":"5105010007","district_id":"5105010","name":"TANGLAD","postal_code":"80771"},{"id":"5105010008","district_id":"5105010","name":"PEJUKUTAN","postal_code":"80771"},{"id":"5105010009","district_id":"5105010","name":"SUANA","postal_code":"80771"},{"id":"5105010010","district_id":"5105010","name":"BATUNUNGGUL","postal_code":"80771"},{"id":"5105010011","district_id":"5105010","name":"KUTAMPI","postal_code":"80771"},{"id":"5105010012","district_id":"5105010","name":"KUTAMPI KALER","postal_code":"80771"},{"id":"5105010014","district_id":"5105010","name":"KAMPUNG TOYAPAKEH","postal_code":"80771"},{"id":"5105010015","district_id":"5105010","name":"LEMBONGAN","postal_code":"80771"},{"id":"5105010016","district_id":"5105010","name":"JUNGUTBATU","postal_code":"80771"}]