[{"id":"6301031001","district_id":"6301031","name":"PANTAI HARAPAN","postal_code":"70853"},{"id":"6301031002","district_id":"6301031","name":"SUNGAI RASAU","postal_code":"30653"},{"id":"6301031003","district_id":"6301031","name":"HANDIL MALUKA","postal_code":"70853"},{"id":"6301031004","district_id":"6301031","name":"HANDIL LABUAN AMAS","postal_code":"70853"},{"id":"6301031005","district_id":"6301031","name":"HANDIL SURUK","postal_code":"70853"},{"id":"6301031006","district_id":"6301031","name":"HANDIL GAYAM","postal_code":"70853"},{"id":"6301031007","district_id":"6301031","name":"KURAU UTARA","postal_code":"70853"},{"id":"6301031008","district_id":"6301031","name":"BUMI HARAPAN","postal_code":"70853"},{"id":"6301031009","district_id":"6301031","name":"HANDIL BABIRIK","postal_code":"70853"},{"id":"6301031010","district_id":"6301031","name":"HANDIL BIRAYANG BAWAH","postal_code":"70853"},{"id":"6301031011","district_id":"6301031","name":"HANDIL BIRAYANG ATAS","postal_code":"70853"}]