[{"id":"7101060001","district_id":"7101060","name":"MOPUSI","postal_code":"95771"},{"id":"7101060002","district_id":"7101060","name":"MATALI BARU","postal_code":"95771"},{"id":"7101060003","district_id":"7101060","name":"BAKAN","postal_code":"83554"},{"id":"7101060004","district_id":"7101060","name":"TANOYAN SELATAN","postal_code":"95771"},{"id":"7101060005","district_id":"7101060","name":"TANOYAN UTARA","postal_code":"95771"},{"id":"7101060006","district_id":"7101060","name":"LOLAYAN","postal_code":"95771"},{"id":"7101060007","district_id":"7101060","name":"TUNGOI II","postal_code":"95771"},{"id":"7101060008","district_id":"7101060","name":"TUNGOI I","postal_code":"95771"},{"id":"7101060009","district_id":"7101060","name":"TAPA AOG","postal_code":"95771"},{"id":"7101060010","district_id":"7101060","name":"ABAK","postal_code":"95771"},{"id":"7101060011","district_id":"7101060","name":"BOMBANON","postal_code":"95771"},{"id":"7101060012","district_id":"7101060","name":"MOPAIT","postal_code":"95771"},{"id":"7101060013","district_id":"7101060","name":"KOPANDAKAN II","postal_code":"95771"},{"id":"7101060014","district_id":"7101060","name":"MENGKANG","postal_code":"95771"}]