[{"id":"7205120001","district_id":"7205120","name":"OMBO","postal_code":"94354"},{"id":"7205120002","district_id":"7205120","name":"TONDO S","postal_code":"94354"},{"id":"7205120003","district_id":"7205120","name":"JONO OGE","postal_code":"94364"},{"id":"7205120004","district_id":"7205120","name":"DAMPAL","postal_code":"94354"},{"id":"7205120005","district_id":"7205120","name":"SIPI","postal_code":"86581"},{"id":"7205120006","district_id":"7205120","name":"TANJUNG PADANG","postal_code":"28752"},{"id":"7205120007","district_id":"7205120","name":"BALENTUMA","postal_code":"62182"},{"id":"7205120008","district_id":"7205120","name":"SIBADO","postal_code":"94354"},{"id":"7205120009","district_id":"7205120","name":"TOMPE","postal_code":"94354"},{"id":"7205120010","district_id":"7205120","name":"LOMPIO","postal_code":"94354"},{"id":"7205120012","district_id":"7205120","name":"LENDE TOVEA","postal_code":"94354"},{"id":"7205120014","district_id":"7205120","name":"UJUMBOU","postal_code":"23774"}]