[{"id":"7306091001","district_id":"7306091","name":"BERUTALLASA","postal_code":"90244"},{"id":"7306091002","district_id":"7306091","name":"PENCONG","postal_code":"90244"},{"id":"7306091003","district_id":"7306091","name":"PARANGLOE","postal_code":"90244"},{"id":"7306091004","district_id":"7306091","name":"LEMBANGLOE","postal_code":"90244"},{"id":"7306091005","district_id":"7306091","name":"TARING","postal_code":"90244"},{"id":"7306091006","district_id":"7306091","name":"TONRORITA","postal_code":"90244"},{"id":"7306091007","district_id":"7306091","name":"BORIMASUNGGU","postal_code":"90653"},{"id":"7306091008","district_id":"7306091","name":"LAUWA","postal_code":"90992"},{"id":"7306091009","district_id":"7306091","name":"BATURAPPE","postal_code":"90244"},{"id":"7306091010","district_id":"7306091","name":"BATUMALONRO","postal_code":"90244"},{"id":"7306091011","district_id":"7306091","name":"JULUKANAYA","postal_code":"90244"}]