[{"id":"7322120013","district_id":"7322120","name":"ROMPU","postal_code":"92961"},{"id":"7322120014","district_id":"7322120","name":"TORADA","postal_code":"22978"},{"id":"7322120015","district_id":"7322120","name":"PONGO","postal_code":"93791"},{"id":"7322120016","district_id":"7322120","name":"POMBAKKA","postal_code":"92957"},{"id":"7322120017","district_id":"7322120","name":"LAPAPA","postal_code":"92961"},{"id":"7322120018","district_id":"7322120","name":"LABA","postal_code":"92961"},{"id":"7322120019","district_id":"7322120","name":"KAPPUNA","postal_code":"92913"},{"id":"7322120020","district_id":"7322120","name":"BONE","postal_code":"85571"},{"id":"7322120021","district_id":"7322120","name":"BALOLI","postal_code":"46312"},{"id":"7322120022","district_id":"7322120","name":"KAMIRI","postal_code":"96265"},{"id":"7322120023","district_id":"7322120","name":"KASIMBONG","postal_code":"92915"},{"id":"7322120024","district_id":"7322120","name":"PANDAK","postal_code":"57281"},{"id":"7322120025","district_id":"7322120","name":"BALIASE","postal_code":"94362"},{"id":"7322120026","district_id":"7322120","name":"MASAMBA","postal_code":"94652"},{"id":"7322120030","district_id":"7322120","name":"SEPAKAT","postal_code":"72211"},{"id":"7322120031","district_id":"7322120","name":"PINCARA","postal_code":"91252"},{"id":"7322120032","district_id":"7322120","name":"LANTANG TALLANG","postal_code":"92961"},{"id":"7322120033","district_id":"7322120","name":"SUMILLIN","postal_code":"92961"},{"id":"7322120034","district_id":"7322120","name":"L E R O","postal_code":"86271"},{"id":"7322120035","district_id":"7322120","name":"UPT MAIPI","postal_code":"96271"},{"id":"7322120036","district_id":"7322120","name":"UPT. SEPAKAT","postal_code":"39265"},{"id":"7322120037","district_id":"7322120","name":"UPT LANTANG TALLANG","postal_code":"96271"}]