[{"id":"8102020015","district_id":"8102020","name":"OHOIWAIT","postal_code":"97661"},{"id":"8102020016","district_id":"8102020","name":"OHOIEL","postal_code":"97661"},{"id":"8102020017","district_id":"8102020","name":"WERKA","postal_code":"97661"},{"id":"8102020018","district_id":"8102020","name":"LER OHOILIM","postal_code":"97661"},{"id":"8102020019","district_id":"8102020","name":"RAHARENG","postal_code":"97661"},{"id":"8102020020","district_id":"8102020","name":"WAUR","postal_code":"97661"},{"id":"8102020021","district_id":"8102020","name":"NGEFUIT","postal_code":"97661"},{"id":"8102020022","district_id":"8102020","name":"WAURTAHAIT","postal_code":"97661"},{"id":"8102020023","district_id":"8102020","name":"YAMTEL","postal_code":"97661"},{"id":"8102020024","district_id":"8102020","name":"OHOINANGAN","postal_code":"97661"},{"id":"8102020025","district_id":"8102020","name":"ELAT","postal_code":"97661"},{"id":"8102020027","district_id":"8102020","name":"OHOILIM","postal_code":"97661"},{"id":"8102020028","district_id":"8102020","name":"FAKO","postal_code":"97661"},{"id":"8102020029","district_id":"8102020","name":"REYAMRU","postal_code":"97661"},{"id":"8102020030","district_id":"8102020","name":"ELRALANG","postal_code":"97661"},{"id":"8102020042","district_id":"8102020","name":"WATUAR","postal_code":"97661"},{"id":"8102020043","district_id":"8102020","name":"MATAHOLAT","postal_code":"97661"},{"id":"8102020044","district_id":"8102020","name":"HARANGUR","postal_code":"97661"},{"id":"8102020045","district_id":"8102020","name":"UDAR","postal_code":"97661"},{"id":"8102020046","district_id":"8102020","name":"DAFTEL","postal_code":"97661"},{"id":"8102020047","district_id":"8102020","name":"KARKARIT","postal_code":"97661"},{"id":"8102020048","district_id":"8102020","name":"RAHARENG ATAS","postal_code":"97661"},{"id":"8102020049","district_id":"8102020","name":"WULURAT","postal_code":"97661"},{"id":"8102020050","district_id":"8102020","name":"NGEFUIT ATAS","postal_code":"97661"},{"id":"8102020051","district_id":"8102020","name":"NABAHENG","postal_code":"97661"},{"id":"8102020052","district_id":"8102020","name":"OHOIWANG","postal_code":"97661"},{"id":"8102020053","district_id":"8102020","name":"FANGAMAS","postal_code":"97661"},{"id":"8102020054","district_id":"8102020","name":"OHOINANGAN ATAS","postal_code":"97661"},{"id":"8102020055","district_id":"8102020","name":"WAKOL","postal_code":"97661"},{"id":"8102020057","district_id":"8102020","name":"SOINRAT","postal_code":"97661"},{"id":"8102020058","district_id":"8102020","name":"WERMAF","postal_code":"97661"},{"id":"8102020059","district_id":"8102020","name":"BOMBAY","postal_code":"97661"},{"id":"8102020060","district_id":"8102020","name":"WATSIN","postal_code":"97661"},{"id":"8102020061","district_id":"8102020","name":"SIRBANTE","postal_code":"97661"},{"id":"8102020062","district_id":"8102020","name":"NGAT","postal_code":"97661"}]