[{"id":"9104100001","district_id":"9104100","name":"MOYEBA","postal_code":"98373"},{"id":"9104100002","district_id":"9104100","name":"MERESTIM","postal_code":"98252"},{"id":"9104100003","district_id":"9104100","name":"MOSUM","postal_code":"98373"},{"id":"9104100004","district_id":"9104100","name":"INOFINA","postal_code":"98373"},{"id":"9104100005","district_id":"9104100","name":"MOYEBA UTARA","postal_code":"98373"},{"id":"9104100006","district_id":"9104100","name":"MOYEBA TIMUR","postal_code":"98373"},{"id":"9104100007","district_id":"9104100","name":"MOYEBA BARAT","postal_code":"98373"},{"id":"9104100009","district_id":"9104100","name":"MESYEM TIMUR","postal_code":"98463"},{"id":"9104100010","district_id":"9104100","name":"MOSROR","postal_code":"99571"}]