[{"id":"9110091001","district_id":"9110091","name":"RENIS","postal_code":"98481"},{"id":"9110091002","district_id":"9110091","name":"SIRE","postal_code":"73753"},{"id":"9110091003","district_id":"9110091","name":"SENI","postal_code":"99571"},{"id":"9110091004","district_id":"9110091","name":"SABES","postal_code":"94882"},{"id":"9110091005","district_id":"9110091","name":"FASE","postal_code":"98154"},{"id":"9110091006","district_id":"9110091","name":"KURASO","postal_code":"25147"},{"id":"9110091007","district_id":"9110091","name":"ARNE","postal_code":"99355"}]