[{"id":"9403200001","district_id":"9403200","name":"KAMDERA","postal_code":"99354"},{"id":"9403200002","district_id":"9403200","name":"MUAIF","postal_code":"99354"},{"id":"9403200003","district_id":"9403200","name":"AMBORA","postal_code":"99354"},{"id":"9403200004","district_id":"9403200","name":"YAUGAPSA","postal_code":"97615"},{"id":"9403200005","district_id":"9403200","name":"DEMTA KOTA","postal_code":"99354"},{"id":"9403200006","district_id":"9403200","name":"YAKORE","postal_code":"99358"},{"id":"9403200007","district_id":"9403200","name":"MURIS KECIL","postal_code":"99354"}]