[{"id":"9409031001","district_id":"9409031","name":"MEOS MANGGUANDI","postal_code":"38387"},{"id":"9409031002","district_id":"9409031","name":"SUPRAIMA","postal_code":"98158"},{"id":"9409031003","district_id":"9409031","name":"SAMBER PASI","postal_code":"98158"},{"id":"9409031004","district_id":"9409031","name":"PASI","postal_code":"62292"},{"id":"9409031005","district_id":"9409031","name":"KARABAI","postal_code":"98158"},{"id":"9409031006","district_id":"9409031","name":"MBROMSI","postal_code":"98158"},{"id":"9409031007","district_id":"9409031","name":"NYANSOREN","postal_code":"98158"},{"id":"9409031008","district_id":"9409031","name":"SARIBRA","postal_code":"98158"},{"id":"9409031009","district_id":"9409031","name":"PADAIDO","postal_code":"98158"},{"id":"9409031010","district_id":"9409031","name":"YERI","postal_code":"98158"},{"id":"9409031011","district_id":"9409031","name":"SASARI","postal_code":"98158"},{"id":"9409031012","district_id":"9409031","name":"YEN MANAINA","postal_code":"98158"},{"id":"9409031013","district_id":"9409031","name":"ANOBO","postal_code":"98158"}]