[{"id":"9416027001","district_id":"9416027","name":"KORUPUN","postal_code":"93461"},{"id":"9416027002","district_id":"9416027","name":"DAGI","postal_code":"99578"},{"id":"9416027004","district_id":"9416027","name":"WEMIN","postal_code":"99578"},{"id":"9416027005","district_id":"9416027","name":"MOROME","postal_code":"99578"},{"id":"9416027007","district_id":"9416027","name":"MOO","postal_code":"99578"},{"id":"9416027008","district_id":"9416027","name":"BATKUK","postal_code":"99578"},{"id":"9416027009","district_id":"9416027","name":"MALDUA","postal_code":"99578"},{"id":"9416027010","district_id":"9416027","name":"AMDUA","postal_code":"99578"},{"id":"9416027011","district_id":"9416027","name":"SOMSEK","postal_code":"99578"},{"id":"9416027012","district_id":"9416027","name":"BASAL","postal_code":"99578"},{"id":"9416027013","district_id":"9416027","name":"YAMDUA","postal_code":"99578"},{"id":"9416027014","district_id":"9416027","name":"DILDAU","postal_code":"99578"}]