[{"id":"9418090004","district_id":"9418090","name":"NUGINI","postal_code":"99569"},{"id":"9418090006","district_id":"9418090","name":"YIKU","postal_code":"99569"},{"id":"9418090007","district_id":"9418090","name":"NILOGABU","postal_code":"99569"},{"id":"9418090008","district_id":"9418090","name":"NAKWI","postal_code":"99569"},{"id":"9418090009","district_id":"9418090","name":"NINI","postal_code":"99568"},{"id":"9418090011","district_id":"9418090","name":"BIMO","postal_code":"99569"},{"id":"9418090012","district_id":"9418090","name":"DUGUNAGEP","postal_code":"99569"}]